livemap/__init__.py
livemap/cli.py
livemap/client.py
livemap/map.py
livemap/server.py
livemap/templates/map.html
fmo_livemap-0.4.0.dist-info/METADATA
fmo_livemap-0.4.0.dist-info/WHEEL
fmo_livemap-0.4.0.dist-info/entry_points.txt
fmo_livemap-0.4.0.dist-info/top_level.txt
fmo_livemap-0.4.0.dist-info/RECORD
