Metadata-Version: 2.1
Name: fmo-livemap
Version: 0.4.0
Summary: Simple way to draw a line on a map in real-time
Author: Gudjon Magnusson
Author-email: gmagnusson@fraunhofer.org
Keywords: Map,real-time
Requires-Python: >=3.7, <4
Requires-Dist: flask >=2.0.0
Requires-Dist: click >=8.0.0
Requires-Dist: Flask-SocketIO >=5.3.0
Requires-Dist: requests >=2.28.2
Requires-Dist: geojson >=3.1.0
